retry_redis/__about__.py
retry_redis/__init__.py
retry_redis/custom_wait.py
retry_redis/decorated_redis.py
retry_redis/retry_decorator.py
retry_redis-1.3.1.dist-info/LICENSE
retry_redis-1.3.1.dist-info/METADATA
retry_redis-1.3.1.dist-info/WHEEL
retry_redis-1.3.1.dist-info/top_level.txt
retry_redis-1.3.1.dist-info/RECORD
